{"userName": "@marcelopellet", "bio": "Sure\u00f1o Gay Casado, viajo de aqu\u00ed a all\u00e1 llevando la palabra de la incidencia en pol\u00edticas p\u00fablicas y UX. Marce para amigos, loco para otros y Estratega de", "outputProfileName": "marceloperez", "bigrams": ["@m", "ma", "ar", "rc", "ce", "el", "lo", "op", "pe", "el", "ll", "le", "et", "Ma", "ar", "rc", "ce", "el", "lo", "o", "P", "P\u00e9", "\u00e9r", "re", "ez"], "pictureURL": "https://pbs.twimg.com/profile_images/788756299592900608/YfM4lxpa_400x400.jpg", "location": "Santiago, Chile", "fullName": "Marcelo P\u00e9rez", "externalUrl": "about.me/marceloperez"}