{"userName": "@TimBroom", "bio": "Husband, father, entrepreneur. CEO of a subscription-based startup, ITProTV, that blends humor and IT education in a talk show format taught by IT Pros.", "outputProfileName": "TimBroom", "bigrams": ["@T", "Ti", "im", "mB", "Br", "ro", "oo", "om", "Ti", "im", "m", "B", "Br", "ro", "oo", "om"], "pictureURL": "https://pbs.twimg.com/profile_images/627445691191660544/r86LZKZE_400x400.jpg", "location": "Gainesville, FL", "fullName": "Tim Broom", "externalUrl": "itpro.tv"}