{"userName": "@TheMusicObsessi", "bio": "What kind of music do we like? The good kind. Get obsessed. info@themusicobsession.com", "outputProfileName": "katerussellftw", "bigrams": ["@T", "Th", "he", "eM", "Mu", "us", "si", "ic", "cO", "Ob", "bs", "se", "es", "ss", "si", "Th", "he", "e", "M", "Mu", "us", "si", "ic", "c", "O", "Ob", "bs", "se", "es", "ss", "si", "io", "on"], "pictureURL": "https://pbs.twimg.com/profile_images/420968788260306944/oEjSidXB_400x400.jpeg", "location": "New York, NY", "fullName": "The Music Obsession", "externalUrl": "themusicobsession.com"}