{"userName": "JenReeves", "bio": "Manager of Social Communications/Training @AARP + Founder @bornjustright.com University of MissouriColumbia Bachelor of Journalism Aquinas College Masters of Management Syracuse University 2 years of study AARP Social communications/trainer Born Just Right Mom Advocate Missouri School of Journalism Associate Professor KOMU 8 Interactive Director WOOD-TV Producer KSBW-TV Producer KBAK-TV Producer Reynolds Journalism Institute Faculty Fellow", "fullName": "Jen Reeves", "externalUrl": ["http://www.twitter.com/jenleereeves", "http://www.flickr.com/photos/jenleereeves", "http://www.flickr.com/photos/reeveskids", "http://www.youtube.com/user/MizzouJen", "http://www.jenleereeves.com", "http://www.bornjustright.com", "http://followgram.me/jenleereeves", "http://www.aarp.org/AARPTEK"], "bigrams": ["Je", "en", "nR", "Re", "ee", "ev", "ve", "es", "Je", "en", "n", "R", "Re", "ee", "ev", "ve", "es"]}