{"userName": "francisca_licarayen", "bio": "Su\u00e9\u00f1eme pues, cataclismo.", "outputProfileName": "licarayen", "bigrams": ["fr", "ra", "an", "nc", "ci", "is", "sc", "ca", "a_", "_l", "li", "ic", "ca", "ar", "ra", "ay", "ye", "en", "Fr", "ra", "an", "nc", "ci", "is", "sc", "ca", "a", "L", "Li", "ic", "ca", "ar", "ra", "ay", "ye", "en"], "pictureURL": "https://scontent-ord1-1.cdninstagram.com/t51.2885-19/s150x150/13628288_1736052036674149_941418499_a.jpg", "fullName": "Francisca Licarayen", "externalUrl": "http://francisca-licarayen.blogspot.com"}