{"userName": "@erikaperugachi", "bio": "\uf8ff Computer Science Engineering @espol | Volunteer @TechoEcu | Developer iOS/Android - NodeJS React Redux @Criptext | Run Swim Gym Tennis Bike", "outputProfileName": "erikaperugachi", "bigrams": ["@e", "er", "ri", "ik", "ka", "ap", "pe", "er", "ru", "ug", "ga", "ac", "ch", "hi", "Er", "ri", "ik", "ka", "a", "P", "Pe", "er", "ru", "ug", "ga", "ac", "ch", "hi"], "pictureURL": "https://pbs.twimg.com/profile_images/765922290135470080/p2H9Qrwx_400x400.jpg", "location": "Guayaquil, Ecuador", "fullName": "Erika Perugachi", "externalUrl": "about.me/erikaperugachi"}