{"userName": "@TriGuyCoaching", "bio": "Triathlon Coach and Exercise Kinesiologist. Former U.S. Navy Rescue Swimmer.", "outputProfileName": "akippingruane", "bigrams": ["@T", "Tr", "ri", "iG", "Gu", "uy", "yC", "Co", "oa", "ac", "ch", "hi", "in", "ng", "Al", "la", "an", "n", "K", "Ki", "ip", "pp", "pi", "in", "ng", "g-", "-R", "Ru", "ua", "an", "ne"], "pictureURL": "https://pbs.twimg.com/profile_images/564815347476209665/VVZmEE3v_400x400.jpeg", "location": "Hoboken, NJ", "fullName": "Alan Kipping-Ruane", "externalUrl": "triguycoaching.com"}