{"userName": "JABusfield", "bio": "writer, editor, lover, happy-dancer... University of North Carolina at Chapel Hill English jab's plethora, LLC Author WebSpark Operations Manager", "fullName": "J. A. Busfield", "externalUrl": ["http://about.me/jabusfield", "http://facebook.com/JABusfield", "http://jabusfield.com/about", "http://twitter.com/jabusfield", "http://facebook.com/jabsLoveLetters", "http://jabsLoveLetters.tumblr.com", "http://jabsloveletters.blogspot.com", "http://twitter.com/jabsLoveLetters", "http://facebook.com/yummygoodness.info", "http://twitter.com/yummy_goodness"], "bigrams": ["JA", "AB", "Bu", "us", "sf", "fi", "ie", "el", "ld", "J.", ".", "A", "A.", ".", "B", "Bu", "us", "sf", "fi", "ie", "el", "ld"]}