{"userName": "@AndreaCosta_ART", "bio": "Creative Director at Stone Digital  |  My thoughts are images, images are my words", "outputProfileName": "andreacosta", "bigrams": ["@A", "An", "nd", "dr", "re", "ea", "aC", "Co", "os", "st", "ta", "a_", "_A", "AR", "RT", "An", "nd", "dr", "re", "ea", "a", "C", "Co", "os", "st", "ta"], "pictureURL": "https://pbs.twimg.com/profile_images/604209947/andrea_costa_400x400.jpg", "location": "Milan", "fullName": "Andrea Costa", "externalUrl": "andreacosta.name"}