{"userName": "AhmedZainal", "bio": "Bahraini PR Specialist by day, electronic music producer by night. University of Waterloo Kinesiology (Ergonomics) Matt Rae Media Owner Tripzaar Co-founder/ UX Design Ontario Power Generation Ergonomist Philanthrokidz Inc. Contest Developer UW Imprint Education Columnist Toyota Motor Manufacturing North America Ergonomist Cargill Ergonomist", "fullName": "Ahmed Zainal", "externalUrl": ["http://www.flickr.com/people/zainal/", "http://www.twitter.com/ahmedzainal", "http://buzzerk.blogspot.com/", "http://buzzerkoniphone.blogspot.com/", "http://picasaweb.google.com/ahmedzainal", "http://www.blogger.com/profile/13840774301067551589", "http://www.google.com/reader/shared/08986904245868818967", "http://soundcloud.com/zainal", "http://www.facebook.com/profile.php?id=510187030&ref=profile"], "bigrams": ["Ah", "hm", "me", "ed", "dZ", "Za", "ai", "in", "na", "al", "Ah", "hm", "me", "ed", "d", "Z", "Za", "ai", "in", "na", "al"]}