{"userName": "@Barbysanti", "bio": "Venezolana. Amante del arte en todas sus expresiones. Lcda. en Comunicaci\u00f3n Social, Publicidad y RRPP #SocialMediaManager. #Coach y emigrante.", "outputProfileName": "barbysanti", "bigrams": ["@B", "Ba", "ar", "rb", "by", "ys", "sa", "an", "nt", "ti", "Ba", "ar", "rb", "ba", "ar", "ra", "a", "R", "Ri", "iv", "va", "as"], "pictureURL": "https://pbs.twimg.com/profile_images/658864813565722624/9zzU8Y_s_400x400.jpg", "location": "Chile", "fullName": "Barbara Rivas", "externalUrl": "barbysanti.wordpress.com"}