{"userName": "ChristineMa", "bio": "MORE SOCIAL NETWORKING!?? Centennial College Post-Grad: Advertising Account Management School of Life/Hard Knocks Can't Settle For Less, University of Toronto English, Sociology By Ikea EKG Technician (you'll need one after eating all those Swedish meatballs and gravy).", "fullName": "Christine Ma", "externalUrl": ["https://www.facebook.com/CHRISTINEHKMA", "http://twitter.com/ChristineHKMa", "http://www.last.fm/user/bonne_pomme", "http://gladabout.livejournal.com/", "https://plus.google.com/108632970572389367770/about", "http://fakebadtaste.files.wordpress.com/2010/11/internet-serious-business-cat.jpg", "http://troll.me/images/victory-baby/internet-serious-business-thumb.jpg", "http://cdn.uproxx.com/wp-content/uploads/2010/10/internetseriousbusiness02.jpg", "http://newsimg.ngfiles.com/184000/184399_internet_serious_business.jpg"], "bigrams": ["Ch", "hr", "ri", "is", "st", "ti", "in", "ne", "eM", "Ma", "Ch", "hr", "ri", "is", "st", "ti", "in", "ne", "e", "M", "Ma"]}