{"userName": "VishwasManjulaaByrappa", "bio": "Consulting Entrepreneur helping you build brand \"You\" Central Saint Martins @ University of the Arts London YSeeker Founder, Editor Rodaasim Founder Byrappa Consulting Entrepreneur We.Create Founding President Rovirek Founder Tech Sentries Co-Founder AVECT Chief Applied Imagineer", "fullName": "Vishwas B", "externalUrl": ["http://www.twitter.com/byrappa", "https://www.facebook.com/Prof.Dr.Byrappa", "http://www.goodreads.com/user/show/2942535", "http://byrappa.tumblr.com/", "http://byrappa.stumbleupon.com", "http://friendfeed.com/byrappa", "http://digg.com/users/byrappa/", "http://byrappa-myblog.blogspot.com/", "http://digg.com/users/Byrappa/", "http://reddit.com/user/Byrappa", "http://www.slideshare.net/Byrappa", "http://www.last.fm/user/byrappa/", "http://disqus.com/Byrappa", "http://youtube.com/user/Byrappa36", "http://www.google.com/profiles/100785811475539342585", "http://byrappa.com/author/byrappa", "http://byrappa.com/notes/author/Byrappa", "https://medium.com/@Byrappa", "http://roamer.ws/author/rovirek/", "http://roamerbaba.com/author/byrappa", "http://senseaboutastrology.com", "http://unlearnrelearn.co/author/byrappa/", "http://vimeo.com/Byrappa", "http://tentationverse.com/author/Rovirek/", "http://byrappa.wordpress.com", "http://byrappa.ws/blog/author/byrappa/", "http://byrappa.ws/ravz/?author=1", "http://byrappa.ws/snaps/author/byrappa/", "http://rovirek.com/blog/author/Rovirek/", "http://wecreate.me/blog/author/rovirek/", "http://d-ream.co/author/rovirek/", "http://www.blogger.com/profile/10626620650015663977", "http://rodaas.im", "http://yseeker.ws", "http://www.librarything.com/profile/Byrappa", "http://www.intensedebate.com/people/Byrappa", "http://www.seesmic.com/Byrappa"], "bigrams": ["Vi", "is", "sh", "hw", "wa", "as", "sM", "Ma", "an", "nj", "ju", "ul", "la", "aa", "aB", "By", "yr", "ra", "ap", "pp", "pa", "Vi", "is", "sh", "hw", "wa", "as", "s", "B"]}