{"userName": "JanZuppinger", "bio": "a wolf in cheap clothes Web-Publisher. DJ. Urban Farmer. Music-Tech- Food-Blogger. I'm not joking, just joking - I am joking, just joking - I'm not joking", "fullName": "Jan Zuppinger", "externalUrl": ["http://pieceoplastic.tumblr.com/", "http://janzuppinger.com", "http://www.linkedin.com/in/janzuppinger", "http://www.facebook.com/people/Jan-Zuppinger/712466859", "https://twitter.com/pieceoplastic", "http://instagram.com/pie0o", "http://www.flickr.com/photos/pieceoplastic/", "http://www.google.com/reader/shared/17390037338577932646", "http://twitter.com/janzuppinger", "https://medium.com/@pieceoplastic", "http://pieceoplastic.tumblr.com/", "http://www.youtube.com/user/pieceoplastic", "http://pieceoplastic.com", "http://web-laun.ch", "http://delicious.com/pieceoplastic", "http://mlkshk.com/user/pieceoplastic"], "bigrams": ["Ja", "an", "nZ", "Zu", "up", "pp", "pi", "in", "ng", "ge", "er", "Ja", "an", "n", "Z", "Zu", "up", "pp", "pi", "in", "ng", "ge", "er"]}