{"userName": "dmJaegerFoto", "bio": "Fotzs, zene, keleti kultra, webfejleszts, termszet... Magyar Gyula Mezgazdasgi / kertszeti szakkzp Krdy Gyula jsgr Iskola / Fggetlen jsgrk Szvetsge jsgrs", "fullName": "dm Jaeger", "externalUrl": ["http://blog.isztan.eu/", "http://twitter.com/isztan", "http://www.flickr.com/photos/termeszetfotok/", "http://instagram.com/blogisztan", "http://picasaweb.google.com/jaegerturk", "http://jaegerturk.blogspot.com/", "http://www.google.com/reader/shared/jaegerturk", "https://soundcloud.com/blogisztan"], "bigrams": ["dm", "mJ", "Ja", "ae", "eg", "ge", "er", "rF", "Fo", "ot", "to", "dm", "m", "J", "Ja", "ae", "eg", "ge", "er"]}