{"userName": "KanyonSayers-Roods", "bio": "Hahashkani - Coyote Woman (Costanaon Oholone + Chumash) Art Institute of California - Sunnyvale Bachelor of Science -Web Design and Interactive Media Gavilan College Liberal Arts Equilar Web and Graphic Contractor Costanoan Indian Reasearch", "fullName": "Kanyon Sayers-Roods", "externalUrl": ["http://www.indiancanyonlife.org/ksr", "http://www.youtube.com/user/IndianCanyonCA1887", "http://picasaweb.google.com/IndianCanyon.Kanyon", "http://www.facebook.com/kanyon.coyote", "http://www.stumbleupon.com/stumbler/kandiekay/", "http://www.indiancanyonlife.org/youthblog", "http://www.askan8v.wordpress.com"], "bigrams": ["Ka", "an", "ny", "yo", "on", "nS", "Sa", "ay", "ye", "er", "rs", "s-", "-R", "Ro", "oo", "od", "ds", "Ka", "an", "ny", "yo", "on", "n", "S", "Sa", "ay", "ye", "er", "rs", "s-", "-R", "Ro", "oo", "od", "ds"]}