{"userName": "CecilyKellogg", "bio": "writer, blogger, mom, wife, bad ass Double Good Media social media, content Babble / Disney Interactive Content & Strategy", "fullName": "Cecily Kellogg", "externalUrl": ["http://www.facebook.com/cecilyk", "http://www.facebook.com/pages/Uppercase-Woman/65377347921", "http://www.flickr.com/people/85486057@N00/", "http://uppercasewoman.com/", "http://uppercasewoman.com/", "http://www.babble.com/contributor/cecilyk/", "http://99designs.com/customer-blog/author/cecilyk/", "http://doublegoodmedia.com", "http://www.uppercasewoman.com"], "bigrams": ["Ce", "ec", "ci", "il", "ly", "yK", "Ke", "el", "ll", "lo", "og", "gg", "Ce", "ec", "ci", "il", "ly", "y", "K", "Ke", "el", "ll", "lo", "og", "gg"]}