{"userName": "@KatieDeLuca", "bio": "Wife & Mommy | Model | Actress | AVO | Writer | Photographer | Chivette | Jedi Master | Blonde with a Brain. INSTAGRAM@ TheKatieDeLuca", "outputProfileName": "katiedeluca", "bigrams": ["@K", "Ka", "at", "ti", "ie", "eD", "De", "eL", "Lu", "uc", "ca", "Ka", "at", "ti", "ie", "e", "D", "De", "eL", "Lu", "uc", "ca"], "pictureURL": "https://pbs.twimg.com/profile_images/637656708039356416/6b9sHO6a_400x400.jpg", "location": "MIAMI", "fullName": "Katie DeLuca", "externalUrl": "KatieDeLuca.com"}