{"userName": "kasihelialg", "bio": "#BatakUnited  #youngontop \nLook at my hand wondering around the paper. Read my world. Look at my face. See what I see.\n#Hailang #Monbebe", "outputProfileName": "kasihelialg", "bigrams": ["ka", "as", "si", "ih", "he", "el", "li", "ia", "al", "lg", "Ka", "as", "si", "ih", "h", "E", "El", "li", "ia", "a", "L", "Lu", "um", "mb", "ba", "an", "n", "G", "Ga", "ao", "ol"], "pictureURL": "https://scontent-ord1-1.cdninstagram.com/t51.2885-19/11849276_738026329654008_1789019515_a.jpg", "fullName": "Kasih Elia Lumban Gaol", "externalUrl": null}