{"userName": "syukranmohdrosli", "bio": "Twitter : @syukranrosli\nFacebook : Syukran Rosli", "outputProfileName": "syukranmohdrosli", "bigrams": ["sy", "yu", "uk", "kr", "ra", "an", "nm", "mo", "oh", "hd", "dr", "ro", "os", "sl", "li", "Mu", "uh", "ha", "am", "mm", "ma", "ad", "d", "S", "Sy", "yu", "uk", "kr", "ra", "an", "n", "M", "Mo", "oh", "hd", "d", "R", "Ro", "os", "sl", "li"], "pictureURL": "https://scontent-ord1-1.cdninstagram.com/t51.2885-19/s150x150/12135182_1054026094654462_1099416975_a.jpg", "fullName": "Muhammad Syukran Mohd Rosli", "externalUrl": "http://about.me/syukranmohdrosli"}