{"userName": "thinknow", "bio": "Living la vida local ~ Los Angeles & Brooklyn", "outputProfileName": "lanehalley", "bigrams": ["th", "hi", "in", "nk", "kn", "no", "ow", "La", "an", "ne", "e", "G", "Go", "ol", "ld", "ds", "st", "to", "on", "ne", "e", "(", "(H", "Ha", "al", "ll", "le", "ey", "y)"], "pictureURL": "https://scontent-ord1-1.cdninstagram.com/t51.2885-19/s150x150/14334593_1297951866903957_1109184310_a.jpg", "fullName": "Lane Goldstone (Halley)", "externalUrl": "http://www.lanegoldstone.com"}