{"userName": "iprickubodyworks", "bio": "18+ years experience  Fakir Alumni  APP Member  NYC Fakir Intensives Comprehensive Piercing", "fullName": "IPRICKU", "externalUrl": ["http://www.twitter.com/ipricku", "https://www.facebook.com/ipricku", "https://www.snapchat.com/add/ipricku", "http://www.instagram.com/ipricku", "http://ipricku.com", "http://www.boundforglorytattoo.com"], "bigrams": ["ip", "pr", "ri", "ic", "ck", "ku", "ub", "bo", "od", "dy", "yw", "wo", "or", "rk", "ks", "IP", "PR", "RI", "IC", "CK", "KU"]}