{"userName": "davidfromkassel", "bio": "27 y/o\nKassel\ud83c\udf07Magnum the cat\ud83d\ude3aPrinz Pi\ud83c\udfb6activism\u270a\u262dvegan\ud83c\udf55chemistry\ud83c\udf86nerdstuff\ud83d\udcf2me\ud83d\udc72 \nsnapchat, twitter: @davidfromkassel\n#keineliebegang", "outputProfileName": "davidredelberger", "bigrams": ["da", "av", "vi", "id", "df", "fr", "ro", "om", "mk", "ka", "as", "ss", "se", "el", "Da", "av", "vi", "id", "d", "R", "Re", "ed", "de", "el", "lb", "be", "er", "rg", "ge", "er"], "pictureURL": "https://scontent-ord1-1.cdninstagram.com/t51.2885-19/s150x150/13249782_540821869453600_151278072_a.jpg", "fullName": "David Redelberger", "externalUrl": "http://about.me/davidredelberger"}