{"userName": "fi0nak", "bio": "\ud83c\udf40 \ud83d\udc99\ud83d\udc9b \u2649\ufe0f \ud83d\udc81\ud83c\udffc\ud83c\udf55\ud83d\udc83\ud83c\udffc\ud83d\udc5c\ud83d\udc95\ud83c\udf7b\ud83d\udc84", "outputProfileName": "fionakearney", "bigrams": ["fi", "i0", "0n", "na", "ak", "F", "I", "I", "O", "O", "N", "N", "A", "A", "", "", "K", "K", "E", "E", "A", "A", "R", "R", "N", "N", "E", "E", "Y"], "pictureURL": "https://scontent-ord1-1.cdninstagram.com/t51.2885-19/s150x150/13696625_1790244781221935_877652047_a.jpg", "fullName": "F I O N A   K E A R N E Y", "externalUrl": null}