{"userName": "IanKath", "bio": "Podcaster with an online Chat Show(http://YourStoryPodcast.com) & advice on Audio Life Stories(http://createyourlifestory.com)once a maker of things. Pattern Making Trade Your Story Create Your Life Story Urban Art Projects Pattern Maker", "fullName": "Ian Kath", "externalUrl": ["http://iankath.com/", "http://www.flickr.com/people/iankath/", "http://www.quora.com/ian-kath", "http://about.me/iankath", "http://twitter.com/#!/iankath", "http://createyourlifestory.wordpress.com/", "http://yourstorypodcast.com/", "http://www.facebook.com/iankath", "http://iankath.com/"], "bigrams": ["Ia", "an", "nK", "Ka", "at", "th", "Ia", "an", "n", "K", "Ka", "at", "th"]}