{"userName": "@drchrisstout", "bio": "Best Selling Author | Clinical Professor/Researcher | Data Wonk | Adventurer | Angel Advisor | (Accidental) Humanitarian", "outputProfileName": "drchrisstout", "bigrams": ["@d", "dr", "rc", "ch", "hr", "ri", "is", "ss", "st", "to", "ou", "ut", "Dr", "r", "C", "Ch", "hr", "ri", "is", "s", "S", "St", "to", "ou", "ut"], "pictureURL": "https://pbs.twimg.com/profile_images/764477743002062848/kvT7ZCWF_400x400.jpg", "location": "Chicago, IL", "fullName": "Dr Chris Stout", "externalUrl": "DrChrisStout.com"}