{"userName": "@princessCH", "bio": "Bloggerin, Travel-Addict & Food Enthusiast - lebt & arbeitet Online (Digital Consultant) mit Offline-Auszeiten & leidet an Fernweh. Feel Good Manager at SBO!", "outputProfileName": "nicolenobs", "bigrams": ["@p", "pr", "ri", "in", "nc", "ce", "es", "ss", "sC", "CH", "Ni", "ic", "co", "ol", "le", "e", "N", "No", "ob", "bs"], "pictureURL": "https://pbs.twimg.com/profile_images/807895046431371264/coOSYr9j_400x400.jpg", "location": "Winterthur, Schweiz", "fullName": "Nicole Nobs", "externalUrl": "princess.ch"}