{"userName": "@FionaGraham", "bio": "Head of Content WorldRemit. Ex-BBC journalist. Ex-tech of business reporter. Loves robots yet fears inevitable AI takeover. Likes plants. http://about.me/fionagraham", "outputProfileName": "fionagraham", "bigrams": ["@F", "Fi", "io", "on", "na", "aG", "Gr", "ra", "ah", "ha", "am", "Fi", "io", "on", "na", "a", "G", "Gr", "ra", "ah", "ha", "am"], "pictureURL": "https://pbs.twimg.com/profile_images/468795822348333056/A4tk6A_U_400x400.jpeg", "location": "London", "fullName": "Fiona Graham", "externalUrl": "about.me/fionagraham"}