{"userName": "@mathieuparisot", "bio": "Incorrigibly optimistic, colorful, ex-digital evangelist @philipsfrance @parrot co-founder #boconceptcotebasque enjoy waves & snow, addicted to music", "outputProfileName": "mathieuparisot", "bigrams": ["@m", "ma", "at", "th", "hi", "ie", "eu", "up", "pa", "ar", "ri", "is", "so", "ot", "Ma", "at", "th", "hi", "ie", "eu", "u", "P", "Pa", "ar", "ri", "is", "so", "ot"], "pictureURL": "https://pbs.twimg.com/profile_images/705475116231213056/GWyi-vnn_400x400.jpg", "location": "Anglet, France", "fullName": "Mathieu Parisot", "externalUrl": "mathieuparisot.com"}