{"userName": "joaquingatica", "bio": "\"In a world without walls, who needs Windows?\" Facultad de Ingeniera - UdelaR Ingeniera en Computacin Instituto Pre/U Colegio Monte VI", "fullName": "Joaqun Gatica", "externalUrl": ["http://about.me/joaquingatica", "https://www.facebook.com/joaquingaticag", "http://www.linkedin.com/in/joaquingatica", "http://joaquingatica.blogspot.com/", "http://vimeo.com/joaquingatica", "http://www.quora.com/Joaqun-Gatica", "http://twitter.com/joaquingatica", "http://quenya101.com"], "bigrams": ["jo", "oa", "aq", "qu", "ui", "in", "ng", "ga", "at", "ti", "ic", "ca", "Jo", "oa", "aq", "qu", "un", "n", "G", "Ga", "at", "ti", "ic", "ca"]}