{"userName": "AlessioFancelloh", "bio": "Creative Technologist / Formateur & Consultant Webmarketing IESN (Namur) Marketing ARJD Marcinelle Langues HEPH-Condorcet, Marcinelle criture Multimdia LiveMentor Marketing Digital - Facebook - Copywriting CM Squad CEO & Social Media Manager Freelance Creative Technologist / Formateur & Consultant Webmarketing Caf Numrique Charleroi Organisateur Wanted Photography Social Media Manager ChambryApp Social Media Community Manager Citruseo Charg de Projet Print & Creation Design Infographiste/Community Manager RTL NewMedia Community Manager (stage) Technofutur TIC Webmaster & SEO (stage) Leester.be Community Manager Slidenjoy Head of Social Media JUSt. Agency Conversation Manager freelance JUSt. Agency Conversation Manager freelance", "fullName": "Alessio Fancello", "externalUrl": ["https://www.linkedin.com/in/alessiof", "http://twitter.com/alessiofancello", "https://www.instagram.com/alessiofancello/", "http://www.slideshare.net/afancello", "http://rookieweb.wordpress.com", "http://cinexperts.wordpress.com", "https://alessiof.com/", "https://www.facebook.com/alessiofcom"], "bigrams": ["Al", "le", "es", "ss", "si", "io", "oF", "Fa", "an", "nc", "ce", "el", "ll", "lo", "oh", "Al", "le", "es", "ss", "si", "io", "o", "F", "Fa", "an", "nc", "ce", "el", "ll", "lo"]}