{"userName": "@pierodibello", "bio": "\u2605 Agile Coach and Software Engineer \u2605 XProgrammer \u2605 Java coder \u2605 Rubyist dreamer", "outputProfileName": "pietrodibello", "bigrams": ["@p", "pi", "ie", "er", "ro", "od", "di", "ib", "be", "el", "ll", "lo", "Pi", "ie", "et", "tr", "ro", "o", "D", "Di", "i", "B", "Be", "el", "ll", "lo"], "pictureURL": "https://pbs.twimg.com/profile_images/698456180457398272/arbUaFvj_400x400.jpg", "location": "Trento", "fullName": "Pietro Di Bello", "externalUrl": "xpepper.github.io/AboutMe/"}