{"userName": "letrainfantome", "bio": "Couture jewelry by Ma\u00eblle Cadoret\n* Made in France *\n* Woldwide shipping *\ninfo@letrainfantome.fr", "outputProfileName": "letrainfantome", "bigrams": ["le", "et", "tr", "ra", "ai", "in", "nf", "fa", "an", "nt", "to", "om", "me", "Le", "e", "T", "Tr", "ra", "ai", "in", "n", "F", "Fa", "an", "nt", "t\u00f4", "\u00f4m", "me"], "pictureURL": "https://scontent-ord1-1.cdninstagram.com/t51.2885-19/s150x150/13649174_1627901197524729_123583087_a.jpg", "fullName": "Le Train Fant\u00f4me", "externalUrl": "http://www.letrainfantome.fr"}