{"userName": "@Caprickah", "bio": "USN Vet. ERAU Grad. Geek. Gamer. Blogger. Twitch: Mystickah. Genealogist. @NASAJuno Social alum.   I do cool things w/ @ExtraLifeJax @MOSHElements.", "outputProfileName": "starbuckspitfire", "bigrams": ["@C", "Ca", "ap", "pr", "ri", "ic", "ck", "ka", "ah", "Ma", "an", "nd", "di", "ie", "e", "M", "Ma", "ar", "rr", "ro", "on"], "pictureURL": "https://pbs.twimg.com/profile_images/828841673966772224/JypdLklc_400x400.jpg", "location": "Jacksonville, Florida", "fullName": "Mandie Marron", "externalUrl": "toasterdreams.com"}