{"userName": "AllenVenablesPhotography", "bio": "Award winning British photographer / creative director based in Malta Manor School New College", "fullName": "Allen Venables", "externalUrl": ["http://www.allenvenables.com", "http://www.facebook.com/WeddingPhotographyMalta", "http://twitter.com/allenvenables", "http://allenvenables.com"], "bigrams": ["Al", "ll", "le", "en", "nV", "Ve", "en", "na", "ab", "bl", "le", "es", "sP", "Ph", "ho", "ot", "to", "og", "gr", "ra", "ap", "ph", "hy", "Al", "ll", "le", "en", "n", "V", "Ve", "en", "na", "ab", "bl", "le", "es"]}