{"userName": "erikatamaura", "bio": "Alumna de @mestresbcn Gestora cultural. Bloguera. #Sonora / Coord. @culturaITSON - @sonorabloggers / Colaboro @ProyectoPuente / Dir. @capuccinoRadio /", "outputProfileName": "erikatamaura", "bigrams": ["er", "ri", "ik", "ka", "at", "ta", "am", "ma", "au", "ur", "ra", "Er", "ri", "ik", "ka", "a", "T", "Ta", "am", "ma", "au", "ur", "ra"], "pictureURL": "https://scontent-ord1-1.cdninstagram.com/t51.2885-19/s150x150/12677145_961048930654858_1298597348_a.jpg", "fullName": "Erika Tamaura", "externalUrl": "http://www.erikatamaura.com"}