{"userName": "jessemontano", "bio": "Smartphone slave, karaoke connoisseur, food pornographer, puppy lover, frequent flyer, beta tester, Florida native, California transplant.", "outputProfileName": "jessemontano", "bigrams": ["je", "es", "ss", "se", "em", "mo", "on", "nt", "ta", "an", "no", "Je", "es", "ss", "se", "e", "M", "Mo", "on", "nt", "ta", "an", "no"], "pictureURL": "https://scontent-ord1-1.cdninstagram.com/t51.2885-19/11374169_402776753245082_430536512_a.jpg", "fullName": "Jesse Montano", "externalUrl": "http://www.jessemontano.com"}