{"userName": "@OscarRuizTome", "bio": "Fot\u00f3grafo especializado en Boda (ceremonia, preboda, postboda). Adem\u00e1s, Fot\u00f3grafo de confianza de Google para #Leonesp", "outputProfileName": "oscarruiztome", "bigrams": ["@O", "Os", "sc", "ca", "ar", "rR", "Ru", "ui", "iz", "zT", "To", "om", "me", "\uf8ffs", "sc", "ca", "ar", "r", "R", "Ru", "ui", "iz", "z", "T", "To", "om", "m\u00e9"], "pictureURL": "https://pbs.twimg.com/profile_images/649176049197125632/_WfYDuth_400x400.jpg", "location": "Leon, Spain", "fullName": "\uf8ffscar Ruiz Tom\u00e9", "externalUrl": "oscarruiztome.com"}