{"userName": "@JaMonkey", "bio": "Lifestyle blog w/ entertainment, recipes, crafts, travel, and tech. Lover of all things #Disney #StarWars #Marvel #Geek @megkcooper", "outputProfileName": "meghancooper", "bigrams": ["@J", "Ja", "aM", "Mo", "on", "nk", "ke", "ey", "Me", "eg", "gh", "ha", "an", "n", "C", "Co", "oo", "op", "pe", "er"], "pictureURL": "https://pbs.twimg.com/profile_images/871001710369665026/HnfvE9M3_400x400.jpg", "location": "Atlanta, GA", "fullName": "Meghan Cooper", "externalUrl": "jamonkey.com"}