{"userName": "SandraSchink", "bio": "Wir sehen die Dinge nicht, wie sie sind. Wir sehen sie, wie wir sind. Anas Nin Fotoatelier.Hamburg Fotografin stern.de/VIEW Fotocommunity Community Management fotoMAGAZIN Online Redakteurin Kleine Niendorfer Lichtbildmanufaktur Photographin Smart & Heart Autorin + Fotografin", "fullName": "Sandra Schink", "externalUrl": ["http://twitter.com/SandraSchink", "http://about.me/shamani", "https://www.xing.com/profile/Sandra_Schink2", "http://www.facebook.com/sandra.schink", "http://klout.com/SandraSchink", "http://co-co-co.de", "http://digiheads.de", "http://socialgrafr.de", "http://sandraschink.de", "http://fotoatelier.hamburg", "http://photomanufaktur.art", "https://www.instagram.com/shamani/"], "bigrams": ["Sa", "an", "nd", "dr", "ra", "aS", "Sc", "ch", "hi", "in", "nk", "Sa", "an", "nd", "dr", "ra", "a", "S", "Sc", "ch", "hi", "in", "nk"]}