{"userName": "DenisSokolov", "bio": "Perpetuum Music / TeleQru / Superhit.TV 416 -   235 -     PERPETUUM MUSIC  ,   FM /       DFM /   -   /  FM    ,          - Warner Music - Ikon Management -   -,      /    ,   -6   -  ,   FM /    ,  ,  ,  ", "fullName": "Denis \u202b\u202c\u200e Sokolov", "externalUrl": ["http://www.egomsk.com", "http://twitter.com/egomaniaque", "http://www.linkedin.com/in/egomsk", "http://facebook.com/densokolov", "http://www.flickr.com/photos/46245564@N00/", "https://profiles.google.com/105847502915406266038/buzz", "http://egomsk.blogspot.com/", "http://gmail.com", "http://www.perpetuummusic.ru", "http://www.superhit.tv", "http://www.retrofm.ru", "http://www.emg.fm"], "bigrams": ["De", "en", "ni", "is", "sS", "So", "ok", "ko", "ol", "lo", "ov", "De", "en", "ni", "is", "s", "\u202b", "\u202b\u202c", "\u202c\u200e", "\u200e", "S", "So", "ok", "ko", "ol", "lo", "ov"]}