{"userName": "BernardoDeNiz", "bio": "Documentary photographer and videographer freelance Photographer Associated Press News agency Photographer Bloomberg Freelance photographer Mexports Photographer ITESO university Professor REUTERS news agency Photographer", "fullName": "Bernardo De Niz", "externalUrl": ["http://www.bernardodeniz.com", "http://picasaweb.google.com/110581921472013785943"], "bigrams": ["Be", "er", "rn", "na", "ar", "rd", "do", "oD", "De", "eN", "Ni", "iz", "Be", "er", "rn", "na", "ar", "rd", "do", "o", "D", "De", "e", "N", "Ni", "iz"]}