{"userName": "CaraPosey-1", "bio": "Marketer, Brand Police, Wordsmith & Change Agent Carnegie Mellon University Arts Management College of Wooster Arts Management", "fullName": "Cara Posey", "externalUrl": ["http://facebook.com/caraposey", "http://www.linkedin.com/in/caraposey", "http://twitter.com/CaraPosey", "https://www.linkedin.com/today/author/7037399-Cara-Posey", "http://www.caraposey.com", "http://www.expertfile.com/blog", "http://baesman.com/blog", "http://blog.pacejet.com", "http://www.linkedin.com/in/caraposey", "http://twitter.com/caraposey", "http://www.caraposey.com", "http://blog.pacejet.com"], "bigrams": ["Ca", "ar", "ra", "aP", "Po", "os", "se", "ey", "y-", "-1", "Ca", "ar", "ra", "a", "P", "Po", "os", "se", "ey"]}