{"userName": "@ivan_xp", "bio": "#TechnologySpecialist #Programmer #SoftwareDeveloper #MobileProgramming #SocialMediaSchool #DigitalMarketing #Makerz http://xn--www-cv5a.ivanoesposito.info\u264ewww.ivanoesposito.info", "outputProfileName": "iesposito", "bigrams": ["@i", "iv", "va", "an", "n_", "_x", "xp", "Iv", "va", "an", "no", "o", "E", "Es", "sp", "po", "os", "si", "it", "to"], "pictureURL": "https://pbs.twimg.com/profile_images/378800000430825008/c2a9c37ec778d10244465fdcb796ff64_400x400.jpeg", "location": "Milan, Lombardy", "fullName": "Ivano Esposito", "externalUrl": "about.me/iesposito"}