{"userName": "FarryAprianto", "bio": "CEO of Tag Design & Grassroot App. Founder of Happinette. SDN Rawa Barat 07 Pagi, Jakarta, Indonesia SMPN 13, Jakarta, Indonesia SMAN 70, Jakarta, Indonesia Universitas Katolik Parahyangan, Bandung, Indonesia Tag Design Website and Application Developer Bank of Tokyo-Mitsubishi Travoo SimmCom Tag Design", "fullName": "Farry Aprianto", "externalUrl": ["http://picasaweb.google.com/farry.aprianto", "http://pearljamindonesia.blogspot.com/", "http://twitter.com/farry", "http://farryaprianto.com"], "bigrams": ["Fa", "ar", "rr", "ry", "yA", "Ap", "pr", "ri", "ia", "an", "nt", "to", "Fa", "ar", "rr", "ry", "y", "A", "Ap", "pr", "ri", "ia", "an", "nt", "to"]}