{"userName": "@altazar", "bio": "Born in Zenica, Bosnia & Hercegovina 1970.\n Lived in Croatia (1977-1987, 1989-1991, 1994-2011). Studied informatics.\n Moved to Frankfurt am Main,", "outputProfileName": "radenko", "bigrams": ["@a", "al", "lt", "ta", "az", "za", "ar", "Ra", "ad", "de", "en", "nk", "ko", "o", "K", "Ko", "os", "si", "i\u0107"], "pictureURL": "https://pbs.twimg.com/profile_images/72966202/altazar_400x400.jpg", "location": "Germany", "fullName": "Radenko Kosi\u0107", "externalUrl": "radenko.kosic.org"}