{"userName": "@suriac", "bio": "Producci\u00f3, #comunicaci\u00f3 i #m\u00e0rqueting cultural a @estenentcultura. Professor de m\u00e0rqueting i #publicitat al @ce_politecnics.", "outputProfileName": "marcsuria", "bigrams": ["@s", "su", "ur", "ri", "ia", "ac", "Ma", "ar", "rc", "c", "S", "Su", "ur", "ri", "i\u00e0", "\u00e0", "C", "Ca", "an", "na", "al", "li", "ia", "as"], "pictureURL": "https://pbs.twimg.com/profile_images/753237630695927808/wAhZnLQc_400x400.jpg", "location": "Barcelona - Girona", "fullName": "Marc Suri\u00e0 Canalias", "externalUrl": "estenentcultura.cat"}