{"userName": "ashtala", "bio": "\u0986\u09ae\u09bf \u09ac\u09be\u0982\u09b2\u09be\u09a6\u09c7\u09b6\u09c0 , \u0986\u09ae\u09bf \u09ac\u09be\u0999\u09cd\u0997\u09be\u09b2\u09c0 , \u0986\u09ae\u09bf \u0997\u09b0\u09cd\u09ac\u09bf\u09a4 (Proud to be a Bangladeshi) \n#ProudBANGLADESHI #JoyBangla \ntwitter: @Ashtala", "outputProfileName": "Ashtala", "bigrams": ["as", "sh", "ht", "ta", "al", "la", "On", "no", "on", "nt", "to", "o", "A", "Ak", "ka", "as", "sh", "h", "|", "|", "\u099c", "\u099c\u09df", "\u09df", "\u09ac", "\u09ac\u09be", "\u09be\u0982", "\u0982\u09b2", "\u09b2\u09be"], "pictureURL": "https://scontent-ord1-1.cdninstagram.com/t51.2885-19/10903719_408653942630571_2071122901_a.jpg", "fullName": "Ononto Akash | \u099c\u09df \u09ac\u09be\u0982\u09b2\u09be", "externalUrl": "http://about.me/Ashtala"}