{"userName": "@karaleung", "bio": "Karaface. Full-time geek. Gamer. Student of the sweet science of bruising. Assistant Trainer for @uclaboxing | \u52e4\u6709\u529f, \u6232\u7121\u76ca. Hard work & dedication. \u1566(\u00f2_\u00f3\u02c7)\u1564", "outputProfileName": "karaface", "bigrams": ["@k", "ka", "ar", "ra", "al", "le", "eu", "un", "ng", "Ka", "ar", "ra", "af", "fa", "ac", "ce"], "pictureURL": "https://pbs.twimg.com/profile_images/745021115542704128/8i-8JM1C_400x400.jpg", "location": "Los Angeles, California", "fullName": "Karaface", "externalUrl": "karaface.com"}