{"userName": "AllieBeauFazekas(AllieBeau)", "bio": "I like mobile web, gin and tonics, and fun UPR (EGCTI) Master Information Science RUM UPR Bibliotecario auxiliar", "fullName": "Allie Beau Fazekas (AllieBeau)", "externalUrl": ["http://www.neverbroken.com", "http://blog.neverbroken.com/"], "bigrams": ["Al", "ll", "li", "ie", "eB", "Be", "ea", "au", "uF", "Fa", "az", "ze", "ek", "ka", "as", "s(", "(A", "Al", "ll", "li", "ie", "eB", "Be", "ea", "au", "u)", "Al", "ll", "li", "ie", "e", "B", "Be", "ea", "au", "u", "F", "Fa", "az", "ze", "ek", "ka", "as", "s", "(", "(A", "Al", "ll", "li", "ie", "eB", "Be", "ea", "au", "u)"]}