{"userName": "CarlosManuelNGuerraAmaral-PT", "bio": "Senior Interaction Designer Univ. van Amsterdam Lusoned Learning Media Adobe Flash Developer Art Base, The International Arts Database B.V. Art Journalist Bertels Holland B.V. Web Development Team Leader Tedopres International B.V. Web & Multimedia Designer", "fullName": "Carlos Manuel N. Guerra Amaral", "externalUrl": ["http://www.twitter.com/flashopen", "http://www.quora.com/Carlos-Guerra-Amaral", "http://www.youtube.com/user/lusoned", "http://flashopen.blogspot.com/", "http://www.flickr.com/flashopen", "http://www.facebook.com/flashopen", "http://www.flashopen.net", "http://www.lusoned.nl", "http://www.civediamo.nl", "http://flashopen.blogspot.com/", "http://www.flickr.com/flashopen", "http://www.facebook.com/flashopen"], "bigrams": ["Ca", "ar", "rl", "lo", "os", "sM", "Ma", "an", "nu", "ue", "el", "lN", "NG", "Gu", "ue", "er", "rr", "ra", "aA", "Am", "ma", "ar", "ra", "al", "l-", "-P", "PT", "Ca", "ar", "rl", "lo", "os", "s", "M", "Ma", "an", "nu", "ue", "el", "l", "N", "N.", ".", "G", "Gu", "ue", "er", "rr", "ra", "a", "A", "Am", "ma", "ar", "ra", "al"]}