{"userName": "@jordigomara", "bio": "Cantautor. Tenor al Cor de Pares de l'Orfe\u00f3 Catal\u00e0 i al Cor de Barcelona http://bandcamp.jordigomara.cat", "outputProfileName": "jordigomara", "bigrams": ["@j", "jo", "or", "rd", "di", "ig", "go", "om", "ma", "ar", "ra", "Jo", "or", "rd", "di", "i", "G", "Go", "om", "ma", "ar", "ra"], "pictureURL": "https://pbs.twimg.com/profile_images/514539735566405632/K7lJmECy_400x400.jpeg", "location": "Vallromanes, Catalunya", "fullName": "Jordi Gomara", "externalUrl": "about.me/jordigomara"}