{"userName": "brattyneil", "bio": "\u2022A blue happy camper. \u2022Amiable but cunning. \u2022Ardent but cynical. *DESCENDANT OF THE GREAT QIN*", "outputProfileName": "brattyneil", "bigrams": ["br", "ra", "at", "tt", "ty", "yn", "ne", "ei", "il", "Ne", "ei", "il", "l", "S", "Sa", "al", "lc", "ce", "ed", "do", "o,", ",", "L", "LP", "PT"], "pictureURL": "https://scontent-ord1-1.cdninstagram.com/t51.2885-19/s150x150/14473931_1003151236474114_5462985997199343616_a.jpg", "fullName": "Neil Salcedo, LPT", "externalUrl": "http://brattyneil.vsco.co"}