{"userName": "@dashable", "bio": "Interested in Space, Chemistry , Machine Learning and Robotics. Planning to be in  in 10 years.", "outputProfileName": "dashable", "bigrams": ["@d", "da", "as", "sh", "ha", "ab", "bl", "le", "#d", "da", "as", "sh", "ha", "ab", "bl", "le", "es", "st", "to", "or", "ri", "ie", "es"], "pictureURL": "https://pbs.twimg.com/profile_images/894140441888686080/7j9_a3Is_400x400.jpg", "location": "Stockholm", "fullName": "#dashablestories", "externalUrl": "Instagram.com/dashable"}