{"userName": "nick.borelli", "bio": "\ud83d\udc6a. I am Borelli Strategies\u203c\ufe0fMarketing for Events & #EventProfs\ud83c\udfaf Speaker\ud83d\udde3 ILEA\ud83d\udcc7 SEARCH Foundation\u2764\ufe0f EMB\u270d\ud83c\udffb SEPA\ud83c\udf93 Events Uncovered\ud83d\udcfd NickBorelli on \ud83d\udc7b", "outputProfileName": "nickjborelli", "bigrams": ["ni", "ic", "ck", "k.", ".b", "bo", "or", "re", "el", "ll", "li", "Ni", "ic", "ck", "k", "B", "Bo", "or", "re", "el", "ll", "li", "i\u2755"], "pictureURL": "https://scontent-ord1-1.cdninstagram.com/t51.2885-19/s150x150/10570085_1138467026187534_1900280460_a.jpg", "fullName": "Nick Borelli\u2755", "externalUrl": "http://www.NickBorell.com"}