{"userName": "@MarcosOlivo", "bio": "Soy un apasionado del MKT Digital. Desarrollo estrategias que aumentan el valor de las marcas y las hacen trascender. Conoce m\u00e1s en @MiCDigital", "outputProfileName": "MarcosOlivo", "bigrams": ["@M", "Ma", "ar", "rc", "co", "os", "sO", "Ol", "li", "iv", "vo", "Ma", "ar", "rc", "co", "os", "s", "O", "Ol", "li", "iv", "vo"], "pictureURL": "https://pbs.twimg.com/profile_images/780848327466233857/j_d_0kD7_400x400.jpg", "location": "M\u00e9xico DF", "fullName": "Marcos Olivo", "externalUrl": "miconsultordigital.com"}