{"userName": "StevenBrynerII", "bio": "The path will begin to emerge once you begin walking upon it. University of Colorado at Boulder English STU Enterprises Account Manager", "fullName": "Steven Bryner II", "externalUrl": ["http://www.youtube.com/user/s0uthw3ststu", "http://www.linkedin.com/in/stevenbryner", "https://www.facebook.com/Steven.Bryner", "https://twitter.com/Steven_Bryner77", "http://myunfinishedthoughts.wordpress.com/", "http://www.stevenebryner2.yolasite.com/", "http://www.raftingcolorado.com/", "http://www.zippingcolorado.com/"], "bigrams": ["St", "te", "ev", "ve", "en", "nB", "Br", "ry", "yn", "ne", "er", "rI", "II", "St", "te", "ev", "ve", "en", "n", "B", "Br", "ry", "yn", "ne", "er", "r", "I", "II"]}