{"userName": "yogurinha_borova", "bio": "SUBSCRIBETE a mi CANAL de Youtube : \nhttp://www.youtube.com/subscription_center?add_user=laYOGURINHA", "outputProfileName": "yogurinha", "bigrams": ["yo", "og", "gu", "ur", "ri", "in", "nh", "ha", "a_", "_b", "bo", "or", "ro", "ov", "va", "yo", "og", "gu", "ur", "ri", "in", "nh", "ha", "a", "b", "bo", "or", "ro", "ov", "va"], "pictureURL": "https://scontent-ord1-1.cdninstagram.com/t51.2885-19/10956848_1546711202277341_1293996749_a.jpg", "fullName": "yogurinha borova", "externalUrl": "http://www.youtube.com/subscription_center?add_user=laYOGURINHA"}