{"userName": "@luca", "bio": "Visualizing communities: https://twitter.com/i/moments/860514628845133825\u00a0\u2026 // Research & Analytics at @freshvanroot", "outputProfileName": "lucahammer", "bigrams": ["@l", "lu", "uc", "ca", "Lu", "uc", "ca", "a", "H", "Ha", "am", "mm", "me", "er", "rV", "Ve", "er", "ri", "if", "fi", "ie", "ed", "d", "a", "ac", "cc", "co", "ou", "un", "nt"], "pictureURL": "https://pbs.twimg.com/profile_images/886249434912358400/yUSP61f1_400x400.jpg", "location": "Altenbeken, Deutschland", "fullName": "Luca HammerVerified account", "externalUrl": "2-blog.net"}