{"userName": "@arambook", "bio": "I am Software Engineer, I graduated from Salahaddin University Software Engineering College at 2009, now I am studying MIT at UTS.", "outputProfileName": "arambook", "bigrams": ["@a", "ar", "ra", "am", "mb", "bo", "oo", "ok", "Ar", "ra", "am", "m", "A", "Az", "za", "ad"], "pictureURL": "https://pbs.twimg.com/profile_images/1089043163/5534_1169827932074_1419240428_30466797_1782809_n_400x400.jpg", "location": "Bankstown, Sydney, Australia", "fullName": "Aram Azad", "externalUrl": "about.me/arambook"}