{"userName": "@MazenJizani", "bio": "\u30c4Welcome To All in My Profile\u30c4 #Training #Development #Team_work #Digital_Marketing #Socialmedia #ThinkingPositive", "outputProfileName": "mazenjizani", "bigrams": ["@M", "Ma", "az", "ze", "en", "nJ", "Ji", "iz", "za", "an", "ni", "Ma", "a", "Z", "Z", "e", "eN", "N", "A", "Al", "lJ", "Ji", "iZ", "Za", "aN", "Ni", "i", "", "\u30c4"], "pictureURL": "https://pbs.twimg.com/profile_images/761669161974112257/ih40TZ8O_400x400.jpg", "location": "Jeddah-KSA | Ireland-Dublin", "fullName": "Ma Z eN AlJiZaNi  \u30c4", "externalUrl": "about.me/mazenjizani"}