{"userName": "@Carolina_1522", "bio": "Marketera digital que echa de menos patinar sobre hielo. Fire built. 86% introvert. ISTJ-A. Friki psic\u00f3pata. I don\u2019t give a fuck about your opinion (\u0a6d\u2022\u0300\u1d17\u2022\u0300\u0a6d)\u2729", "outputProfileName": "Carolina1522", "bigrams": ["@C", "Ca", "ar", "ro", "ol", "li", "in", "na", "a_", "_1", "15", "52", "22", "\u2729\u2102", "\u2102a", "ar", "ro", "ol", "li", "in", "na", "a\u2729"], "pictureURL": "https://pbs.twimg.com/profile_images/893584961336463360/F2-WM9tC_400x400.jpg", "location": "Entre AdWords & Viktuuri hell", "fullName": "\u2729\u2102arolina\u2729", "externalUrl": "about.me/Carolina_1522"}