{"userName": "shopunearthed", "bio": "UNEARTHED - House Of Leather since 2006. Maker of leather goods. Lover of flowers. Mother of 2 wild boys.\nTwitter + Pinterest: @UNEARTHED", "outputProfileName": "UNEARTHED", "bigrams": ["sh", "ho", "op", "pu", "un", "ne", "ea", "ar", "rt", "th", "he", "ed", "UN", "NE", "EA", "AR", "RT", "TH", "HE", "ED", "D\u2122"], "pictureURL": "https://scontent-ord1-1.cdninstagram.com/t51.2885-19/10919548_1521741371447425_1505865619_a.jpg", "fullName": "UNEARTHED\u2122", "externalUrl": "http://UNEARTHED.etsy.com"}