{"userName": "davidkirsch", "bio": "http://www.sakara.com/blogs/mag/slife-mag-find-your-guru-david-kirsch-of-madison-square-club-nyc", "outputProfileName": "DavidKirsch", "bigrams": ["da", "av", "vi", "id", "dk", "ki", "ir", "rs", "sc", "ch", "Da", "av", "vi", "id", "d", "K", "Ki", "ir", "rs", "sc", "ch"], "pictureURL": "https://scontent-ord1-1.cdninstagram.com/t51.2885-19/s150x150/14716618_998630360247544_6965621971182682112_a.jpg", "fullName": "David Kirsch", "externalUrl": "http://www.davidkirschwellness.com"}