{"userName": "WilliamFrankhouser", "bio": "SoCal Web Dev Brogrammer, BFF+, Father, Husband, Photog, World of Tanks/Steam/Play4Free Gamer, Christian Thunderbird School of Global Management Advanced Information Technology and Business Management US Global Marketing Group, LLC Mobile and E Commerce Global Mgr.", "fullName": "William Frankhouser", "externalUrl": ["http://twitter.com/wilzdezign", "http://flickr.com/photos/wilzdezign", "https://www.facebook.com/pages/WilzDezign/129585620394955", "http://www.panoramio.com/user/wilzdezign", "http://www.youtube.com/user/wilzdezign", "http://www.wilzdezign.com", "http://www.everettcc.edu"], "bigrams": ["Wi", "il", "ll", "li", "ia", "am", "mF", "Fr", "ra", "an", "nk", "kh", "ho", "ou", "us", "se", "er", "Wi", "il", "ll", "li", "ia", "am", "m", "F", "Fr", "ra", "an", "nk", "kh", "ho", "ou", "us", "se", "er"]}