{"userName": "@buckmasterflash", "bio": "Author. Chef. Gamer. Producer / TV Host @KVIEPBS. Technologist. I pronounce every letter in macabre, salmon, and sarcasm. Fmr: @intel. #PBSNerd", "outputProfileName": "heathbuckmaster", "bigrams": ["@b", "bu", "uc", "ck", "km", "ma", "as", "st", "te", "er", "rf", "fl", "la", "as", "sh", "He", "ea", "at", "th", "h", "B", "Bu", "uc", "ck", "km", "ma", "as", "st", "te", "er", "rV", "Ve", "er", "ri", "if", "fi", "ie", "ed", "d", "a", "ac", "cc", "co", "ou", "un", "nt"], "pictureURL": "https://pbs.twimg.com/profile_images/906370828454977536/MPHe1OS1_400x400.jpg", "location": "Sacramento, CA", "fullName": "Heath BuckmasterVerified account", "externalUrl": "heathbuckmaster.com"}