{"userName": "SezinKoehler", "bio": "Writer, editor, cultural mythologist, global nomad. Occidental College Anthropology Confidential Researcher & Writer Ghostwoods Books Author Institute of Sociology, Prague Manuscript Editor University of Cologne Manuscript Editor Charles University in Prague Manuscript Editor University of Torino Manuscript Editor", "fullName": "Sezin Koehler", "externalUrl": ["http://picasaweb.google.com/sezin.koehler", "http://twitter.com/SezinKoehler", "http://www.flickr.com/people/sezinia/", "http://www.youtube.com/user/sezinkoehler", "http://hybridMONSTER.org", "http://www.americanmonsters.org", "http://www.youtube.com/user/SezinKoehler", "http://www.expatharem.com", "http://www.thedisplacednation.com", "http://www.redroom.com", "http://thesocietypages.org/socimages/", "http://msmagazine.com/blog/", "http://www.anythinghorror.com"], "bigrams": ["Se", "ez", "zi", "in", "nK", "Ko", "oe", "eh", "hl", "le", "er", "Se", "ez", "zi", "in", "n", "K", "Ko", "oe", "eh", "hl", "le", "er"]}