{"userName": "@mindthegip", "bio": "A curious Italian #Designer, looking at the World from #Milan. Senior #Digital Designer and PM @Philipp_Plein. User first", "outputProfileName": "mindthegip", "bigrams": ["@m", "mi", "in", "nd", "dt", "th", "he", "eg", "gi", "ip", "Gi", "iu", "us", "se", "ep", "pp", "pe", "e", "C", "Ca", "as", "su", "uc", "cc", "ci", "io"], "pictureURL": "https://pbs.twimg.com/profile_images/796649635112775680/L4z3gXLO_400x400.jpg", "location": "Around the World", "fullName": "Giuseppe Casuccio", "externalUrl": "mindthegip.com"}