{"userName": "JasonJordanAustralia", "bio": "TV/Radio Presenter. Tech Commentator. Agitator. Rabble Rouser. You probably shouldn't take me seriously. May contain partial nudity. Jingleberry Farm Entrepreneur Sky News Tech Commentator Channel 7 Tech Commentator 6PR Talkback Presenter PCGURU CEO IBM GE Capital IT Solutions Woodside Petroleum Sealcorp Water Corporation Western Australian Ministry of Justice Woolworths", "fullName": "Jason Jordan", "externalUrl": ["http://www.google.com/reader/shared/01294913151396354186", "http://claimid.com/jasonjordan", "http://www.dandyid.org/id/jasonjordan", "http://www.flickr.com/photos/jasonjordan/", "http://www.last.fm/user/jasonjordan/", "http://www.facebook.com/jasondjordan", "http://live.yahoo.com/profile/mrjasonjordan", "http://picasaweb.google.com/jason.jordan", "http://www.flickr.com/people/jasonjordan/", "http://about.me/jasonjordan", "http://www.quora.com/jason-jordan", "http://twitter.com/jasonjordan", "http://www.linkedin.com/in/jasondjordan", "http://www.youtube.com/user/mrjasonjordan", "http://jordanandson.com", "http://www.jasonjordan.com.au"], "bigrams": ["Ja", "as", "so", "on", "nJ", "Jo", "or", "rd", "da", "an", "nA", "Au", "us", "st", "tr", "ra", "al", "li", "ia", "Ja", "as", "so", "on", "n", "J", "Jo", "or", "rd", "da", "an"]}