{"userName": "dellingtontattoos", "bio": "Owner of Under the Gun, Inc. In Terre Haute, IN\nTattooing 11 years\nNothing here but tattoos and art!", "outputProfileName": "dwanellington", "bigrams": ["de", "el", "ll", "li", "in", "ng", "gt", "to", "on", "nt", "ta", "at", "tt", "to", "oo", "os", "D'", "'W", "Wa", "an", "n", "E", "El", "ll", "li", "in", "ng", "gt", "to", "on"], "pictureURL": "https://scontent-ord1-1.cdninstagram.com/t51.2885-19/11244608_500112583488898_1797345072_a.jpg", "fullName": "D'Wan Ellington", "externalUrl": "http://facebook.com/utgtattoos"}