{"userName": "JoGo416", "bio": "Copywriter, Social Media Strategist, Writer, Technophile, Fashionista, Foodie, and Registered Nurse Uber Developer Advocate AppDynamics Developer Evangelist", "fullName": "Jo Go (Ms. JAG)", "externalUrl": ["http://twitter.com/msjag", "http://http;//twitter.com/chowhoundgta", "http://twitter.com/urbantoronto", "http://facebook.com/expertrns", "http://twotorontocopywriters.com"], "bigrams": ["Jo", "oG", "Go", "o4", "41", "16", "Jo", "o", "G", "Go", "o", "(", "(M", "Ms", "s.", ".", "J", "JA", "AG", "G)"]}