{"userName": "AdamChristianson", "bio": "Just a Mac Geek with a few friends and a dream. California Polytechnic State University Graphic Communication Las Lomas High School", "fullName": "Adam Christianson", "externalUrl": ["http://www.google.com/reader/shared/maccast", "http://www.facebook.com/themaccast", "http://about.me/adamchristianson", "http://macobserver.com", "http://theiosshow.com", "http://www.britishtechnetwork.com/category/mac", "http://www.maccast.com/"], "bigrams": ["Ad", "da", "am", "mC", "Ch", "hr", "ri", "is", "st", "ti", "ia", "an", "ns", "so", "on", "Ad", "da", "am", "m", "C", "Ch", "hr", "ri", "is", "st", "ti", "ia", "an", "ns", "so", "on"]}