{"userName": "iamfelipa", "bio": "\ud83d\ude4f\ud83c\udffcLuke 1:37\nDallas based | Lifestyle Blogger\nBlog: Life with Felipa\n\ud83d\udd58 9-5: Marketing Coordinator \nUTA Alum '13 \ud83d\udc34\n\u2709\ufe0f felipavillegas@gmail.com", "outputProfileName": "felipavillegas", "bigrams": ["ia", "am", "mf", "fe", "el", "li", "ip", "pa", "Fe", "el", "li", "ip", "pa", "a", "V", "Vi", "il", "ll", "le", "eg", "ga", "as"], "pictureURL": "https://scontent-ord1-1.cdninstagram.com/t51.2885-19/s150x150/13696643_1409319385750557_1115249256_a.jpg", "fullName": "Felipa Villegas", "externalUrl": "http://bit.ly/fallbeanboots"}